{
  "generated_at": "2026-06-27T11:16:23Z",
  "date": "2026-06-27",
  "battles": [
    {
      "id": "2026-06-27-sports-4ed4efe0",
      "category": "Sports",
      "battle_title": "Head-to-Head: Tiger Woods vs Rory McIlroy — The Internet Decides!",
      "option_a": "Tiger Woods",
      "option_b": "Rory McIlroy",
      "voting_api_key": "battles/sports/tiger-woods-vs-rory-mcilroy/2026-06-27",
      "timestamp": "2026-06-27T11:16:23Z"
    },
    {
      "id": "2026-06-27-tech-7ff8d53a",
      "category": "Tech",
      "battle_title": "Netflix vs Disney+ — The Battle That's Breaking Tech Twitter Right Now!",
      "option_a": "Netflix",
      "option_b": "Disney+",
      "voting_api_key": "battles/tech/netflix-vs-disney/2026-06-27",
      "timestamp": "2026-06-27T11:16:23Z"
    },
    {
      "id": "2026-06-27-economy-cee12859",
      "category": "Economy",
      "battle_title": "Oil vs Natural Gas: Wall Street Is Watching — Which Side Are You On?",
      "option_a": "Oil",
      "option_b": "Natural Gas",
      "voting_api_key": "battles/economy/oil-vs-natural-gas/2026-06-27",
      "timestamp": "2026-06-27T11:16:23Z"
    }
  ]
}